textual_timepiece/__about__.py
textual_timepiece/__init__.py
textual_timepiece/_activity_heatmap.py
textual_timepiece/_demo.py
textual_timepiece/_extra.py
textual_timepiece/_types.py
textual_timepiece/_utility.py
textual_timepiece/activity_heatmap.py
textual_timepiece/constants.py
textual_timepiece/py.typed
textual_timepiece/utility.py
textual_timepiece/pickers/__init__.py
textual_timepiece/pickers/_base_picker.py
textual_timepiece/pickers/_date_picker.py
textual_timepiece/pickers/_datetime_picker.py
textual_timepiece/pickers/_time_picker.py
textual_timepiece/pickers/_timerange_picker.py
textual_timepiece/timeline/__init__.py
textual_timepiece/timeline/_base_timeline.py
textual_timepiece/timeline/_timeline_entry.py
textual_timepiece/timeline/_timeline_layouts.py
textual_timepiece/timeline/_timeline_manager.py
textual_timepiece-0.5.1.dist-info/METADATA
textual_timepiece-0.5.1.dist-info/WHEEL
textual_timepiece-0.5.1.dist-info/entry_points.txt
textual_timepiece-0.5.1.dist-info/licenses/LICENSE.md
textual_timepiece-0.5.1.dist-info/RECORD
