Metadata-Version: 2.4
Name: textual-timepiece
Version: 0.5.1
Summary: Various time related widgets & functionality for Textual.
Project-URL: Repository, https://github.com/ddkasa/textual-timepiece
Project-URL: Issues, https://github.com/ddkasa/textual-timepiece/issues
Project-URL: Changelog, https://github.com/ddkasa/textual-timepiece/tree/main/docs/CHANGELOG.md
Project-URL: Coverage, https://app.codecov.io/gh/ddkasa/textual-timepiece
Project-URL: Documentation, https://ddkasa.github.io/textual-timepiece/
Author-email: David Kasakaitis <davidkasakaitis@proton.me>
License-Expression: MIT
License-File: LICENSE.md
Keywords: activity,date,heatmap,textual,time,timeline,tui,whenever,widget
Classifier: Development Status :: 3 - Alpha
Classifier: Intended Audience :: Developers
Classifier: License :: OSI Approved :: MIT License
Classifier: Natural Language :: English
Classifier: Programming Language :: Python :: 3
Classifier: Programming Language :: Python :: 3.10
Classifier: Programming Language :: Python :: 3.11
Classifier: Programming Language :: Python :: 3.12
Classifier: Programming Language :: Python :: 3.13
Classifier: Topic :: Software Development :: Libraries :: Python Modules
Classifier: Topic :: Terminals
Classifier: Typing :: Typed
Requires-Python: >=3.10
Requires-Dist: textual>=2.1.0
Requires-Dist: whenever<0.9.0,>=0.8.0
